{
  "taskId": "T-test-4.5",
  "status": "completed",
  "summary": "Full e2e regression suite verified after fix-1. All 126 tests pass (0 failures, 23.2s runtime). Both graduated specs (task-executor) and existing specs (init-justfile, justfile-e2e-integration, justfile-execution, scope-resolution, plugin-content, gen-test-scripts) pass cleanly.",
  "filesCreated": [],
  "filesModified": [],
  "keyDecisions": [],
  "testsPassed": 126,
  "testsFailed": 0,
  "coverage": -1.0,
  "acceptanceCriteria": [
    { "criterion": "just test-e2e passes (full suite, no --feature flag)", "met": true },
    { "criterion": "All graduated and existing specs pass", "met": true }
  ],
  "notes": "Retry after fix-1 resolved pre-existing e2e test failures. Suite is now green."
}
